commcare_api/__init__.py
commcare_api/commcare_api.py
commcare_api-0.1.0a0.dist-info/METADATA
commcare_api-0.1.0a0.dist-info/WHEEL
commcare_api-0.1.0a0.dist-info/top_level.txt
commcare_api-0.1.0a0.dist-info/RECORD
