Metadata-Version: 2.1
Name: commcare-api
Version: 0.1.0a0
Summary: Python library for interacting with the CommCareHQ API
Home-page: https://github.com/thecassion/commcare-api
Author: Pierre Robentz Cassion
Author-email: pierrerobentz.cassion@gmail.com
License: MIT
Classifier: Development Status :: 3 - Alpha
Classifier: Intended Audience :: Developers
Classifier: License :: OSI Approved :: MIT License
Classifier: Programming Language :: Python
Classifier: Programming Language :: Python :: 3
Classifier: Programming Language :: Python :: 3.6
Classifier: Programming Language :: Python :: 3.7
Classifier: Programming Language :: Python :: 3.8
Classifier: Programming Language :: Python :: 3.9
Classifier: Programming Language :: Python :: 3.10
Classifier: Programming Language :: Python :: 3.11
Requires-Dist: requests
